Workbook

Sheet Data
A1: Variable | B1: Tipo de dato | C1: Valor | D1: Origen | E1: Poderacion | F1: Variable Python / Cálculo
A2: RADICADO | B2: str | C2: 1062331885_260318151220 | D2: Valida1 | F2: radicado (generado en valida_1: f"{id}_{yymmddHHMMSS}")
A3: NOMBRE | B3: str | C3: MAHECHA MARTINEZ JEISON ANDREY | D3: Taynasoft | F3: campos_taynasoft["name"] ← data["primerNombre"] + segundoNombre + primerApellido + segundoApellido
A4: CÉDULA | B4: int | C4: 1023903374 | D4: Usuario en Bot WA | F4: chat_input["id"]
A5: GENERO | B5: str | C5: M | D5: Taynasoft | F5: NO se usa en el motor. Si se quisiera: Experian basicInformation.gender / genderDesc
A6: MONTO SOLICITADO | B6: int | C6: 10000000 | D6: Usuario en Bot WA | F6: campos_taynasoft["req_amount"] ← chat_input["req_amount"]
A7: LINEA | B7: int | C7: CONSUMO | D7: Usuario en Bot WA | F7: campos_taynasoft["des_line"] ← chat_input["credit_line"] (mapeo credit_line_base)
A8: F. ESTUDIO DE CRÉDITO | B8: datetime.date | C8: 45731 | D8: Automático | F8: datetime.now() (automático en generar_radicado)
A9: TIPO DE ASOCIADO | B9: str | C9: COLABORADOR | D9: Taynasoft | E9: =IF(C9="COLABORADOR",30,IF(C9="ADMINISTRATIVO",30,IF(C9="EXTRABAJADOR",-10,IF(C9="FAMILIAR",0,IF(C9="SIEMENS MUNDIAL",-10,IF(C9="MISION",0,0)))))) | F9: campos_taynasoft["associate"] / ["associate_desc"] ← data["idTipoAsociado"]
A10: FORMA DE PAGO SOLICITUD | B10: str | C10: NOMINA | D10: Usuario en Bot WA | E10: =IF(C10="NOMINA",25,IF(C10="VENTANILLA",-20,IF(OR(C10="DEBITO AUTOMATICO",C10="DEBITO AUTOMÁTICO"),-10,0))) | F10: campos_taynasoft["payment"] / ["desc_pay"] ← data["idFormaPago"]
A11: JURISDICCIÓN | B11: str | C11: CUNDINAMARCA | D11: Taynasoft | E11: =IF(C11="CUNDINAMARCA",10,-10) | F11: campos_taynasoft["jurisdiction"] ← data["idJurisdiccion"]
A12: NIVEL DE ESTUDIOS | B12: str | C12: Universitaria | D12: Taynasoft | E12: =IF(C12="Universitaria",10,IF(C12="Especializacion",10,IF(C12="Secundaria",-10,IF(C12="Tecnica",5,IF(C12="Tecnológica",5,IF(C12="Maestria",10,IF(C12="Analfabetismo",-10,IF(C12="Magister",10,IF(C12="Doctorado",10,0))))))))) | F12: campos_taynasoft["education_lvl"] / ["education_lvl_desc"] ← data["idNivelEstudio"]
A13: EDAD | B13: int | C13: 25 | D13: Taynasoft | E13: =IF(AND(C13>=20,C13<=30),10,IF(AND(C13>=31,C13<=40),15,IF(AND(C13>=41,C13<=50),13,IF(AND(C13>=51,C13<=70),10,IF(AND(C13>=71,C13<=80),-5,IF(C13>=81,-20,0)))))) | F13: campos_taynasoft["age"] ← data["edad"]
A14: TIPO DE VIVIENDA | B14: str | C14: PROPIA | D14: Taynasoft | E14: =IF(C14="PROPIA",10,IF(C14="ARRIENDO",-5,IF(C14="FAMILIAR",0,IF(C14="PROPIA CON HIPOTECA",5,IF(C14="OTRA",-5,0))))) | F14: campos_taynasoft["housing_type"] / ["housing_type_desc"] ← data["idTipoVivienda"]
A15: TIPO DE CONTRATO | B15: str | C15: INDEFINIDO | D15: Taynasoft | E15: =IF(C15="INDEFINIDO",15,IF(C15="FIJO",-10,IF(C15="OBRA LABOR",-20,0))) | F15: campos_taynasoft["contract_type"] / ["contract_type_desc"] ← data["idTipoContrato"]
A16: ACTIVIDAD ECONÓMICA | B16: str | C16: EMPLEADO | D16: Taynasoft | E16: =IF(C16="PENSIONADO",0,IF(C16="EMPLEADO",5,IF(C16="CESANTE",-20,IF(C16="RENTISTA DE CAPITAL",-20,0)))) | F16: campos_taynasoft["economic_act"] / ["economic_activity_desc"] ← data["idActividadEconomica"]
A17: Fecha de Ingreso a la Empresa | B17: datetime.date | C17: 36566 | D17: Taynasoft | F17: campos_taynasoft["company_entry"] ← data["fechaIngresoEmpresa"]
A18: Fecha de Ingreso a FESICOL | B18: datetime.date | C18: 36932 | D18: Taynasoft | F18: campos_taynasoft["fesicol_entry"] ← data["fechaIngresoFondo"]
A19: Salario Asociado | B19: float | C19: 3500000 | D19: Mareigua - TU - Experian(x) | F19: campos_taynasoft["salary_amt"] ← data["salario"]
A20: Descuentos Créditos Fesicol | B20: float | C20: 200000 | D20: Taynasoft | F20: campos_taynasoft["fesicol_cred"] ← data["descuentoCreditoFondo"]
A21: Descuentos Ahorros Fesicol | B21: float | C21: 0 | D21: Taynasoft | F21: campos_taynasoft["fesicol_sav"] ← data["descuentoAhorroFondo"]
A22: Otros Descuentos Fesicol | B22: float | C22: 0 | D22: Taynasoft | F22: campos_taynasoft["fesicol_misc"] ← data["otroDescuentoFondo"] (también fesicol_other ← data["otroDescuento"])
A23: Cuotas externas | B23: float | C23: 300000 | D23: Experian | F23: acumuladores_experian["ext_installment"] (CALCULADO en procesar_response: suma cuotas externas paymentType=="0" y normalized_id != "860004840")
A24: Ingresos ( Otros) | B24: float | C24: 200000 | D24: Usuario en Bot WA | F24: campos_taynasoft["other_income"] ← data["otroIngresoSalarial"] (también income_ext ← data["otroIngreso"])
A25: Saldo de Cartera Actual Consumo (Interno) | B25: float | C25: 2400000 | D25: Taynasoft | F25: campos_taynasoft["bal_cons_in"] ← data["saldoCarteraConsumo"]
A26: Saldo de Cartera Actual Vehículo (Interno) | B26: float | C26: 0 | D26: Taynasoft | F26: campos_taynasoft["bal_veh_in"] ← data["saldoCarteraVehiculo"]
A27: Saldo de Cartera Actual Vivienda (Interno) | B27: float | C27: 0 | D27: Taynasoft | F27: campos_taynasoft["bal_hous_in"] ← data["saldoCarteraVivienda"]
A28: Ahorro Permanente | B28: float | C28: 10000000 | D28: Taynasoft | F28: campos_taynasoft["perm_saving"] ← data["ahorroPermanente"]
A29: Ahorros a la vista | B29: float | C29: 5000000 | D29: Taynasoft | F29: campos_taynasoft["avail_saving"] ← data["ahorroVista"]
A30: PLAZO DE CRÉDITO | B30: int | C30: 48 | D30: Usuario en Bot WA | E30: =IF(C7="CONSUMO",IF(C30<=36,10,IF(C30<=60,5,0)),IF(C7="VIVIENDA",IF(C30<=120,10,0),0)) | F30: chat_input["credit_term"] (→ credit_term en el motor)
A31: Saldo Cartera Externa Consumo | B31: float | C31: 9000000 | D31: Experian | F31: acumuladores_experian["bal_cons_ext"] (CALCULADO: suma debtBalance de obligaciones consumo, normalized_id != "860004840")
A32: Saldo Total Cartera Externa Vivienda | B32: float | C32: 257000000 | D32: Experian | F32: acumuladores_experian["bal_hous_ext"] (CALCULADO: suma debtBalance de obligaciones vivienda, typeOfCredit == 3)
A33: Saldo Total Cartera Externa Vehiculo | B33: float | C33: 0 | D33: Experian | F33: acumuladores_experian["bal_veh_ext"] (CALCULADO: suma debtBalance vehículo, accountTypeDesc in {LVE,CVH,CVD})
A34: Amortizacion a Capital actual | B34: float | C34: 100000 | D34: Taynasoft | F34: campos_taynasoft["curr_amort"] ← data["amortizacionCapital"]
A35: Amortizacion a Capital Solicitud | B35: float | C35: 723492 | D35: Taynasoft | F35: transfor_data["proj_installment"] (CALCULADO: (req_amount*i)/(1-(1+i)^-n) + req_amount*0.00017)
A36: Cuota Ahorro Permanente | B36: float | C36: 50000 | D36: Taynasoft | F36: campos_taynasoft["perm_fee"] ← data["cuotaAhorroPermanente"]
A37: DIAS DE MORA INTERNA | B37: int | C37: 0 | D37: Taynasoft | E37: =IF(C37=0,50,IF(AND(C37>=1,C37<=10),0,IF(AND(C37>=11,C37<=30),-50,IF(AND(C37>=31,C37<=60),-80,IF(C37>60,-100,0))))) | F37: campos_taynasoft["late_days_in"] ← data["diasMoraInterna"]
A38: CALIFICACIÓN CENTRAL DE RIESGOS | B38: int | C38: 674 | D38: Experian | E38: =IF(C38=0,50,IF(C38>=890,280,IF(C38>=800,250,IF(C38>=701,150,IF(C38>=501,50,IF(C38>=351,-100,IF(C38>=1,-200,0))))))) | F38: credit_score ← response["ReportHDCplus"]["models"][0]["scoreValue"] (Experian)

Sheet Processing
A1: Variable | B1: Tipo de dato | C1: Valor | D1: Origen | E1: Ponderacion | F1: Variable Python / Cálculo
A2: ANTIGÜEDAD LABORAL | B2: int | C2: =DAYS360(Data!C17,TODAY())/360 | D2: Cálculo en motor | E2: =IF(C2<3,0,IF(C2<5,5,IF(C2<=10,10,15))) | F2: transfor_data["company_age"] (CALCULADO: años entre company_entry y hoy, en calcular_edad)
A3: ANTIGÜEDAD COMO ASOCIADO | B3: int | C3: =DAYS360(Data!C18,TODAY())/360 | D3: Cálculo en motor | E3: =IF(C3<3,0,IF(C3<5,5,IF(C3<=10,10,15))) | F3: transfor_data["fesicol_age"] (CALCULADO: años entre fesicol_entry y hoy)
A4: NIVEL DE INGRESOS | B4: int | C4: =Data!C19/1750905 | D4: Cálculo en motor | E4: =IF(C4<2,10,IF(C4<4,20,IF(C4<6,30,IF(C4<8,40,50)))) | F4: transfor_data["nivel_ingresos"] (CALCULADO: salary_amt / SM, SM = 1.423.500)
A5: CAPACIDAD DE DESCUENTO | B5: int | C5: =+((Data!C19)-(C6+C7+C9+Data!C20+Data!C21+Data!C22))/(Data!C19) | D5: Cálculo en motor | E5: =IF(C5<0.4,-50,IF(C5<=0.5,20,IF(C5<=0.6,40,50))) | F5: transfor_data["capacidad_descuento"] (CALCULADO: (ingresos - egresos) / ingresos)
A6: Descuentos de Ley (Salud Pensión) | B6: float | C6: =Data!C19*8% | D6: Cálculo en motor | F6: legal_deduct (CALCULADO: salary_amt * 0.08)
A7: Descuentos de Fondo de Solidaridad | B7: float | C7: =Data!C19*1% | D7: Cálculo en motor | F7: solidarity_deduction (CALCULADO: salary_amt * 0.01)
A8: Tasa_Nominal_Mes_Vencido | B8: int | C8: 0.0167 | D8: Cálculo en motor | F8: campos_taynasoft["interest_rate"] (CALCULADO en calcular_interest_rate según credit_line y credit_term)
A9: Cuota de Proyectada solicitud de Crédito | B9: float | C9: =PMT(C8,Data!C30,-Data!C6) | D9: Cálculo en motor | F9: transfor_data["proj_installment"] (CALCULADO: fórmula PMT + 0.017% del monto)
A10: CAPACIDAD DE PAGO | B10: int | C10: =+((Data!C19+Data!C24)-(C6+C7+C9+Data!C20+Data!C21+Data!C22+Data!C23))/(Data!C19+Data!C24) | D10: Cálculo en motor | E10: =IF(C10<=0.24,-100,IF(C10<=0.3,80,IF(C10<=0.4,90,100))) | F10: transfor_data["capacidad_pago"] (CALCULADO: (ingresos+income_ext - egresos-ext_installment) / (ingresos+income_ext))
A11: APALANCAMIENTO FINANCIERO | B11: int | C11: =+(Data!C6+Data!C25+Data!C26+Data!C27)/(Data!C28+Data!C29) | D11: Cálculo en motor | E11: =IF(C11<=10,20,IF(C11<=20,0,IF(C11<=30,-10,-20))) | F11: transfor_data["leverage"] (CALCULADO: (req_amount + bal_cons_in + bal_veh_in + bal_hous_in) / (perm_saving + avail_saving))
A12: CUPO MÁXIMO TOTAL ENDEUDAMIENTO | B12: float | C12: =Data!C6+Data!C25+Data!C26+Data!C27 | D12: Cálculo en motor | E12: =IF(AND(C29="Real Hipoteca",C12<2164400000),0,IF(AND(C29="Real Hipoteca",C12>=2164400000),-100,IF(C12<1082200000,0,-100))) | F12: transfor_data["max_debt"] (CALCULADO: req_amount + bal_cons_in + bal_veh_in + bal_hous_in)
A13: RECIPROCIDAD | B13: int | C13: =+(Data!C6+Data!C25+Data!C26+Data!C27)/(Data!C28) | D13: Cálculo en motor | E13: =IF(C13<=4,20,IF(C13<=8,10,IF(C13<=15,0,IF(C13<=30,-50,-100)))) | F13: transfor_data["reciprocity"] (CALCULADO: (req_amount + saldos internos) / perm_saving)
A14: NIVEL DE ENDEUDAMIENTO CONSUMO | B14: int | C14: =+IF(Data!C7="CONSUMO",(Data!C6+Data!C25+Data!C31)/(Data!C19),(Data!C25+Data!C31)/(Data!C19)) | D14: Cálculo en motor | E14: =IF(C14=0,40,IF(C14<=8,40,IF(C14<=15,0,IF(C14<=20,-100,-200)))) | F14: transfor_data["nivel_endeudamiento_consumo"] (CALCULADO: depende de credit_line, ratio sobre salary_amt)
A15: NIVEL DE ENDEUDAMIENTO - ACTIVOS | B15: int | C15: =+IF(OR(Data!C7="VIVIENDA",Data!C7="VEHICULO"),(Data!C6+Data!C26+Data!C27+Data!C32+Data!C33)/(Data!C19),(Data!C26+Data!C27+Data!C32+Data!C33)/(Data!C19)) | D15: Cálculo en motor | E15: =IF(C15=0,0,IF(C15<=30,40,IF(C15<=40,0,-100))) | F15: transfor_data["nivel_endeudamiento_activos"] (CALCULADO: ratio activos / salary_amt)
A16: ENDEUDAMIENTO TOTAL (Informativo) | B16: float | C16: =+Data!C6+Data!C25+Data!C26+Data!C27+Data!C31+Data!C32+Data!C33 | D16: Cálculo en motor | F16: transfor_data["total_debt"] (CALCULADO: req_amount + saldos internos + externos)
A17: NIVEL DE ENDEUDAMIENTO TOTAL (Informativo) | B17: int | C17: =C15+C14 | D17: Cálculo en motor | F17: transfor_data["nivel_endeudamiento_total"] (CALCULADO: nivel_endeudamiento_consumo + nivel_endeudamiento_activos)
A18: SOLVENCIA PATRIMONIAL | B18: int | C18: =+(C19-C20)/(C19+Data!C28+Data!C29) | D18: Cálculo en motor | E18: =IF(C18>0.25,40,IF(C18>=0.01,10,IF(C18=0,0,-100))) | F18: transfor_data["equity"] (CALCULADO: (asset_value - liab_value) / (asset_value + perm_saving + avail_saving))
A19: Valor Total Activos | B19: int | C19: 203000000 | D19: Cálculo en motor | F19: campos_taynasoft["asset_value"] ← data["totalActivo"]
A20: Valor Total Pasivos | B20: int | C20: =+Data!C6+Data!C25+Data!C26+Data!C27+Data!C31+Data!C32+Data!C33 | D20: Cálculo en motor | F20: transfor_data["liab_value"] (CALCULADO: req_amount + saldos internos + externos)
A21: VALOR DE RIESGO | B21: int | C21: =IF((Data!C6+Data!C25+Data!C26+Data!C27)-(Data!C28+C24+C26+C28)<0,0,(Data!C6+Data!C25+Data!C26+Data!C27)-(Data!C28+C24+C26+C28)) | D21: Cálculo en motor | E21: =IF(C21=0,100,IF(C21/1160000<=30,50,-200)) | F21: transfor_data["valor_riesgo"] (CALCULADO: max(0, (req_amount + saldos internos) - (perm_saving + indem_value + hipoteca_ajustada + prenda_ajustada)))
A22: Valor Posible Indemnización | B22: int | C22: 6500000 | D22: Cálculo en motor | F22: Valor base de indemnización (hardcodeado / parámetro)
A23: % Indemnización | B23: float | C23: =+IF(C2<1,100%,IF(AND(C2>=1,C2<=4),90%,IF(AND(C2>4,C2<=8),80%,IF(AND(C2>8,C2<=12),75%,IF(AND(C2>12,C2<=16),65%,50%))))) | D23: Cálculo en motor | F23: transfor_data["indem_pct"] (CALCULADO: porcentaje según company_age)
A24: Indemnizacion | B24: int | C24: =C22*C23 | D24: Cálculo en motor | F24: transfor_data["indem_value"] (CALCULADO: valor_indem_base * indem_pct)
A25: % Hipotecas | B25: int | C25: 190000000 | D25: Cálculo en motor | F25: campos_taynasoft["mortg_value"] ← data["valorHipoteca"]
A26: Hipotecas | B26: int | C26: =C25*75% | D26: Cálculo en motor | F26: transfor_data["hipoteca_ajustada"] (CALCULADO: mortg_value * 0.75)
A27: % Prendas | B27: int | C27: 0 | D27: Cálculo en motor | F27: campos_taynasoft["pledge_value"] ← data["valorPrenda"]
A28: Prendas | B28: int | C28: =C27*50% | D28: Cálculo en motor | F28: transfor_data["prenda_ajustada"] (CALCULADO: pledge_value * 0.50)
A29: GARANTÍA | B29: str | C29: Real Hipoteca | D29: Cálculo en motor | E29: =IF(C29="Real Hipoteca",20,IF(C29="Real Prenda",10,IF(C29="Firma Personal",5,0))) | F29: transfor_data["garantia"] (CALCULADO: "Real Hipoteca" / "Real Prenda" / "Firma Personal" según req_mortgage / req_pledge)
A30: Descubierto | B30: float | C30: =(Data!C25+Data!C26+Data!C27+Data!C6)-(Data!C28) | D30: Cálculo en motor | F30: transfor_data["overdraft"] (CALCULADO: (saldos internos + req_amount) - perm_saving)
A31: RECUPERACION DESCUBIERTO | B31: int | C31: =+C30/(Data!C34+Data!C35+Data!C36) | D31: Cálculo en motor | E31: =IF(C31<=12,20,IF(C31<=24,15,IF(C31<=36,10,IF(C31<=60,5,0)))) | F31: transfor_data["recuperacion_descubierto"] (CALCULADO: overdraft / (curr_amort + proj_installment + perm_fee))
A32: RECUPERACIÓN VALOR DE RIESGO | B32: int | C32: =+C21/(Data!C34+Data!C35+Data!C36) | D32: Cálculo en motor | E32: =IF(C32<=12,20,IF(C32<=24,15,IF(C32<=36,5,IF(C32<=60,0,-50)))) | F32: transfor_data["risk_recover"] (CALCULADO: valor_riesgo / (curr_amort + proj_installment + perm_fee))
A33: SCORING FESICOL | B33: int | D33: Cálculo en motor | E33: =Data!E9+Data!E10+Data!E11+Data!E12+Data!E13+Data!E14+Data!E15+Data!E16+Data!E30+Data!E37+Data!E38+Processing!E2+Processing!E3+Processing!E4+Processing!E5+Processing!E10+Processing!E11+Processing!E12+Processing!E13+Processing!E14+Processing!E15+Processing!E18+Processing!E21+Processing!E29+Processing!E31+Processing!E32 | F33: transfor_data["SCORING_FESICOL"] (CALCULADO: perf_soc + perfil_fro + perfil_habito)
A34: INSTANCIA DE APROBACIÓN | B34: str | D34: Cálculo en motor | E34: =IF(E33<=400,"JUNTA DIRECTIVA",IF(AND(E33>400,E33<=500),"COMITÉ DE CRÉDITO",IF(AND(E33>500,E33<=749),"GERENCIA","JEFE DE CREDITO Y CARTERA"))) | F34: transfor_data["decision_nivel_autoridad"] (CALCULADO: ≤400 JUNTA, ≤500 COMITÉ, ≤749 GERENCIA, >749 JEFE)

Sheet Leyenda
A1: Leyenda de colores (columna F)
A3: Verde | B3: campos_taynasoft[...] ← Taynasoft.data[...] (parsear_taynasoft)
A4: Azul | B4: acumuladores_experian[...] o credit_score (Experian, procesar_response)
A5: Naranja | B5: chat_input[...] (lo manda el bot / payload)
A6: Amarillo | B6: transfor_data[...] CALCULADO dentro de motor()
A7: Gris | B7: Automático (datetime.now, generar_radicado)
A10: Notas
A11: • 'parsear_taynasoft(data, chat_input)' (líneas 300-579 de complete_fesicol.py) traduce el bloque 'data' de Taynasoft a campos_taynasoft.
A12: • 'procesar_response(response, tablas)' (líneas 648-775) recorre liabilities y creditCard de Experian y separa interno (NIT 860004840 = Fesicol) vs externo.
A13: • 'motor(campos_taynasoft, acumuladores_experian, chat_input, credit_score)' (línea 782) construye transfor_data con todos los cálculos.
A14: • SM = 1.423.500 (salario mínimo, línea 789).
A15: • La decisión final (línea 1634) sale del SCORING_FESICOL = perf_soc + perfil_fro + perfil_habito.
A16: • La fila 5 (GENERO) actualmente no se usa en el motor; el código no la lee de Taynasoft.
A17: • La fila 22 (Valor Posible Indemnización) aparece hardcoded en 6.500.000 en el Excel; en el motor el campo equivalente es indem_value (calculado).
